freezefs/__main__.py
freezefs/archive.py
freezefs/ffsextract.py
freezefs/ffsmount.py
freezefs-2.4.dist-info/METADATA
freezefs-2.4.dist-info/WHEEL
freezefs-2.4.dist-info/licenses/LICENSE
freezefs-2.4.dist-info/RECORD
