Metadata-Version: 2.3
Name: freezefs
Version: 2.4
Summary: freezefs - Create self-mounting or self-extracting compressed archives for MicroPython
Project-URL: Homepage, https://github.com/bixb922/freezefs
Project-URL: Bug Tracker, https://github.com/bixb922/freezefs/issues
Project-URL: Blog, https://solazyasueto.blogspot.com
Author-email: Hermann von Borries <bixb922@gmail.com>
License: MIT License
License-File: LICENSE
Classifier: Intended Audience :: Developers
Classifier: License :: OSI Approved :: MIT License
Classifier: Operating System :: OS Independent
Classifier: Programming Language :: Python :: 3
Classifier: Programming Language :: Python :: 3.9
Classifier: Programming Language :: Python :: 3.10
Classifier: Programming Language :: Python :: 3.11
Classifier: Programming Language :: Python :: Implementation :: CPython
Classifier: Programming Language :: Python :: Implementation :: MicroPython
Classifier: Topic :: Desktop Environment :: File Managers
Requires-Python: >=3.9
